RegisterImages/WithDicomReg.py
RegisterImages/__init__.py
RegisteringImages-0.1.3.dist-info/LICENSE.txt
RegisteringImages-0.1.3.dist-info/METADATA
RegisteringImages-0.1.3.dist-info/WHEEL
RegisteringImages-0.1.3.dist-info/top_level.txt
RegisteringImages-0.1.3.dist-info/RECORD
