Metadata-Version: 2.1
Name: RegisteringImages
Version: 0.1.3
Summary: Tools for reading DICOM registration file along with two SimpleITK Images (probably from DICOM) and resampling the moving image. Major help from Bastien Rigaud in creation.
Home-page: https://github.com/brianmanderson/RegisteringImages
Author: Brian Mark Anderson
Author-email: markba122@gmail.com
License: UNKNOWN
Platform: UNKNOWN
Classifier: Programming Language :: Python :: 3
Classifier: License :: OSI Approved :: GNU Affero General Public License v3
Requires-Dist: SimpleITK
Requires-Dist: numpy
Requires-Dist: pydicom
